dt_tools/__init__.py
dt_tools/cli/demos/__init__.py
dt_tools/cli/demos/dt_geoloc_demo.py
dt_tools/cli/demos/dt_misc_demo.py
dt_tools/cli/demos/dt_misc_sound_demo.py
dt_tools/cli/demos/dt_weather_demo.py
dt_tools/geoloc/__init__.py
dt_tools/geoloc/census_geoloc.py
dt_tools/geoloc/geoloc.py
dt_tools/geoloc/sun.py
dt_tools/sound/__init__.py
dt_tools/sound/detector.py
dt_tools/sound/helper.py
dt_tools/weather/__init__.py
dt_tools/weather/common.py
dt_tools/weather/weather.py
dt_tools/weather/weather_forecast_alert.py
dt_misc-0.2.20.dist-info/LICENSE
dt_misc-0.2.20.dist-info/METADATA
dt_misc-0.2.20.dist-info/WHEEL
dt_misc-0.2.20.dist-info/RECORD
