Metadata-Version: 2.3
Name: dt-misc
Version: 0.2.20
Summary: Misc. utility packages (geoloc, weather, sound, ...)
License: MIT
Keywords: python,dt-tools
Author: Al DAmico
Author-email: JavaWiz1@hotmail.com
Requires-Python: >=3.10,<4.0
Classifier: License :: OSI Approved :: MIT License
Classifier: Programming Language :: Python
Classifier: Programming Language :: Python :: 3
Classifier: Programming Language :: Python :: 3.10
Classifier: Programming Language :: Python :: 3.11
Classifier: Programming Language :: Python :: 3.12
Classifier: Programming Language :: Python :: 3.13
Requires-Dist: dt-foundation
Requires-Dist: dt-net
Requires-Dist: gtts (>=2.5.2,<3.0.0)
Requires-Dist: loguru
Requires-Dist: pyaudio (>=0.2.14,<0.3.0)
Requires-Dist: timezonefinder
Requires-Dist: tzdata ; sys_platform == "win32"
Project-URL: Repository, https://github.com/JavaWiz1/dt-misc
